{
    "title":"Lyd",
    "category": "navigation",
    "importance": 2,
    "preface": "Ved bruk av lyd må du ta høyde for døve, eller brukere med nedsatt hørsel. Informasjon skal presenteres på en måte brukerne kan oppfatte. Det vil si at informasjon ikke kun skal være tilgjengelig ved hjelp av en enkelt sans. Bruk gjerne et tekstlig alternativ. Hvis lyden er i en kontekst hvor timingen er viktig for budskapet, må du bruke et tekstbasert mediaalternativ som lar brukeren få informasjon til riktig tid. <br>Brukeren må også kunne pause eller stoppe lyden, samt regulere lydstyrken.",
    "reference": [{
        "url": "http://uu.difi.no/veiledning/suksesskriterier/121-bare-lyd-og-bare-video-forh%C3%A5ndsinnspilt",
        "title": "Difis Suksesskriterier, bare lyd og bare video (forhåndsinnspilt)"
    },{
        "url": "http://uu.difi.no/veiledning/suksesskriterier/122-teksting-forh%C3%A5ndsinnspilt",
        "title": "Difis Suksesskriterier, teksting (forhåndsinnspilt)"
    },{
        "url": "http://uu.difi.no/veiledning/suksesskriterier/142-styring-av-lyd",
        "title": "Difis Suksesskriterier, styring av lyd"
    }],
    "relevant": [{
        "url": "http://uu.difi.no/veiledning/suksesskriterier/retningslinje-12-tidsbaserte-medier",
        "title": "Om tidsbaserte medier"
    },{
        "url": "http://uu.difi.no/veiledning/suksesskriterier/111-ikke-tekstlig-innhold",
        "title": "Suksesskriterie 1.1.1 Ikke tekstlig innhold"
    },{
        "url": "http://uu.difi.no/veiledning/suksesskriterier/133-sensoriske-egenskaper",
        "title": "Suksesskriterie 1.3.3 Sensoriske egenskaper"
    },{
        "url": "http://uu.difi.no/veiledning/suksesskriterier/147-lav-eller-ingen-bakgrunnslyd-unntatt",
        "title": "Retningslinje 1.4.7 Lav eller ingen bakgrunnslyd (AAA)"
    }]
}

